{
 "ARICA": "1000000",
 "AZAPA": "1040000",
 "IQUIQUE": "1100000",
 "FUERZA AEREA": "1113000",
 "ALTO HOSPICIO": "1130000",
 "HUARA": "1140000",
 "FUERTE CONDELL": "1150000",
 "AEROPUERTO DIEGO ARACENA": "1160000",
 "PICA": "1170000",
 "POZO ALMONTE": "1180000",
 "CHUQUICAMATA": "1070000",
 "SIERRA GORDA": "1320000",
 "CALAMA": "1390000",
 "SAN PEDRO DE ATACAMA": "1410000",
 "BODEGA CODELCO": "1420000",
 "ANTOFAGASTA": "1240000",
 "PUERTO COLOSO": "1270000",
 "LA NEGRA": "1271000",
 "CERRO MORENO": "1272000",
 "TALTAL": "1300000",
 "MEJILLONES": "1310000",
 "TOCOPILLA": "1340000",
 "MARIA ELENA": "1360000",
 "CHANARAL": "1490000",
 "DIEGO DE ALMAGRO": "1500000",
 "COPIAPO": "1530000",
 "BAHIA INGLESA": "1532000",
 "EL SALVADOR": "1533000",
 "INCA DE ORO": "1534000",
 "PAIPOTE": "1535000",
 "CALDERA": "1570000",
 "TIERRA AMARILLA": "1580000",
 "VALLENAR": "1610000",
 "FREIRINA": "1630000",
 "HUASCO": "1640000",
 "LA SERENA": "1700000",
 "PERALILLO LA SERENA": "1720000",
 "LA HERRADURA": "1721000",
 "PLAYA BLANCA": "1722000",
 "GUANAQUEROS": "1730000",
 "RIVADAVIA": "1731000",
 "TONGOY": "1732000",
 "TOTORALILLO": "1733000",
 "LA HIGUERA": "1740000",
 "ANDACOLLO": "1750000",
 "VICUNA": "1760000",
 "PAIHUANO": "1770000",
 "COQUIMBO": "1780000",
 "DIAGUITAS": "1782000",
 "PUERTO VELERO": "1793000",
 "PISCO ELQUI": "1794000",
 "MORRILLOS": "1800000",
 "MONTE GRANDE": "1801000",
 "LAS TACAS": "1802000",
 "EL MOLLE": "1803000",
 "EL PALQUI": "1080000",
 "PICHASCA": "1650000",
 "SOTAQUI": "1792000",
 "OVALLE": "1840000",
 "RIO HURTADO": "1870000",
 "MONTE PATRIA": "1880000",
 "COMBARBALA": "1890000",
 "PUNITAQUI": "1900000",
 "LOS MOLLES": "1783000",
 "QUILIMARI": "1790000",
 "PICHIDANGUI": "1791000",
 "ILLAPEL": "1930000",
 "LOS VILOS": "1940000",
 "SALAMANCA": "1950000",
 "CANELA": "1960000",
 "LA LIGUA": "2030000",
 "PETORCA": "2040000",
 "CABILDO": "2050000",
 "LOS ANDES": "2100000",
 "SAN ESTEBAN": "2120000",
 "CALLE LARGA": "2130000",
 "RINCONADA": "2140000",
 "SAN FELIPE": "2170000",
 "PUTAENDO": "2190000",
 "SANTA MARIA": "2200000",
 "PANQUEHUE": "2210000",
 "LLAILLAY": "2220000",
 "CATEMU": "2230000",
 "NOGALES": "2300000",
 "HIJUELAS": "2310000",
 "SALADILLO": "2362000",
 "ARTIFICIO": "2363000",
 "CATAPILCO": "2370000",
 "CHINCOLCO": "2371000",
 "EL MELON": "2373000",
 "PICHICUY": "2380000",
 "ZAPALLAR": "2060000",
 "PAPUDO": "2070000",
 "LIMACHE": "2240000",
 "SAN PEDRO DE LIMACHE": "2241000",
 "QUILLOTA": "2260000",
 "LA CRUZ": "2280000",
 "LA CALERA": "2290000",
 "OLMUE": "2330000",
 "VALPARAISO": "2340000",
 "PENUELAS": "2372000",
 "LAGUNA VERDE": "2390000",
 "CURAUMA": "2391000",
 "QUILPUE": "2420000",
 "MAITENCILLO": "2421000",
 "PLAYA ANCHA": "2430000",
 "PENABLANCA": "2431000",
 "HORCON": "2432000",
 "EL BELLOTO": "2440000",
 "COLLIGUAY": "2441000",
 "CACHAGUA": "2442000",
 "VILLA ALEMANA": "2450000",
 "CASABLANCA": "2480000",
 "QUINTERO": "2490000",
 "PUCHUNCAVI": "2500000",
 "CONCON": "2510000",
 "VIÑA DEL MAR": "2511000",
 "LO ABARCA": "2531000",
 "BUCALEMU": "2540000",
 "MIRASOL": "2541000",
 "VENTANAS": "2542000",
 "QUINTAY": "2550000",
 "LAS CRUCES": "2551000",
 "TABOLANGO": "2552000",
 "SAN SEBASTIAN": "2560000",
 "EL LLECO": "2561000",
 "LLO LLEO": "2562000",
 "LAS BRISAS": "2570000",
 "ISLA NEGRA": "2571000",
 "BARRANCAS": "2572000",
 "RODELILLO": "2580000",
 "RENACA": "2581000",
 "ISLA JUAN FERNANDEZ": "2600000",
 "SAN ANTONIO": "2660000",
 "CARTAGENA": "2680000",
 "EL TABO": "2690000",
 "EL QUISCO": "2700000",
 "ALGARROBO": "2710000",
 "SANTO DOMINGO": "2720000",
 "PLACILLA VINA DEL MAR": "3100000",
 "CURACAVI": "9630000",
 "ISLA DE PASCUA": "2770000",
 "PROVIDENCIA": "7500000",
 "LAS CONDES": "7550000",
 "VITACURA": "7630000",
 "LO BARNECHEA": "7690000",
 "LA DEHESA": "7710000",
 "ÑUÑOA": "7750000",
 "MACUL": "7810000",
 "LA REINA": "7850000",
 "PENALOLEN": "7910000",
 "LA CISTERNA": "7970000",
 "EL BOSQUE": "8010000",
 "SAN BERNARDO": "8050000",
 "SANTA ANA DE CHENA": "8054000",
 "SANTA ROSA DE CHENA": "8070000",
 "SAN JOSE": "8071000",
 "RINCONADA DE MAIPU": "8080000",
 "NOS": "8081000",
 "MALLOCO": "8082000",
 "PUENTE ALTO": "8150000",
 "LA FLORIDA": "8240000",
 "SANTIAGO": "8320000",
 "INDEPENDENCIA": "8380000",
 "RECOLETA": "8420000",
 "PEDRO AGUIRRE CERDA": "8460000",
 "QUINTA NORMAL": "8500000",
 "CONCHALI": "8540000",
 "HUECHURABA": "8580000",
 "RENCA": "8640000",
 "QUILICURA": "8700000",
 "LA GRANJA": "8780000",
 "LA PINTANA": "8820000",
 "SAN RAMON": "8860000",
 "SAN MIGUEL": "8900000",
 "SAN JOAQUIN": "8940000",
 "LO PRADO": "8980000",
 "PUDAHUEL": "9020000",
 "CERRO NAVIA": "9080000",
 "PUANGUE": "9081000",
 "CRUCE LAS ARANAS": "9090000",
 "EL PAICO": "9091000",
 "LONGO VILOS": "9100000",
 "LONQUEN": "9101000",
 "MALLARAUCO": "9110000",
 "LO ESPEJO": "9120000",
 "ESTACION CENTRAL": "9160000",
 "CERRILLOS": "9200000",
 "MAIPU": "9250000",
 "COLINA": "9340000",
 "CHICUREO": "9350000",
 "LAMPA": "9380000",
 "TIL TIL": "9420000",
 "SAN JOSE DE MAIPO": "9460000",
 "PIRQUE": "9480000",
 "BUIN": "9500000",
 "ALTO JAHUEL": "9501000",
 "PAINE": "9540000",
 "CALERA DE TANGO": "9560000",
 "MELIPILLA": "9580000",
 "BOLLENAR": "9581000",
 "POMAIRE": "9582000",
 "CHOLQUI": "9590000",
 "MARIA PINTO": "9620000",
 "ALHUE": "9650000",
 "SAN PEDRO": "9660000",
 "TALAGANTE": "9670000",
 "PADRE HURTADO": "9710000",
 "PENAFLOR": "9750000",
 "CARMEN ALTO": "9760000",
 "PABELLON": "9761000",
 "ISLA DE MAIPO": "9790000",
 "MAIPO": "9800000",
 "EL MONTE": "9810000",
 "RANCAGUA": "2820000",
 "TUNICHE": "2830000",
 "PUNTA CORTES": "2831000",
 "OLIVAR BAJO": "2832000",
 "OLIVAR ALTO": "2840000",
 "LOS LIRIOS": "2841000",
 "LO MIRANDA": "2842000",
 "LA COMPANIA": "2843000",
 "GULTRO": "2850000",
 "DONIHUE": "2851000",
 "COPEQUEN": "2852000",
 "GRANEROS": "2880000",
 "SAN FRANCISCO DE MOSTAZAL": "2890000",
 "CODEGUA": "2900000",
 "MACHALI": "2910000",
 "COYA": "2911000",
 "EL OLIVAR": "2920000",
 "REQUINOA": "2930000",
 "QUINTA DE TILCOCO": "2960000",
 "PICHIDEGUA": "2980000",
 "PEUMO": "2990000",
 "COLTAUCO": "3000000",
 "COINCO": "3010000",
 "LAS CABRAS": "3030000",
 "SARMIENTO": "2821000",
 "LONTUE": "2912000",
 "CURICO": "3340000",
 "TENO": "3360000",
 "ROMERAL": "3370000",
 "MOLINA": "3380000",
 "LOS NICHES": "3381000",
 "SAGRADA FAMILIA": "3390000",
 "HUALANE": "3400000",
 "LICANTEN": "3410000",
 "RAUCO": "3430000",
 "CUREPTO": "3570000",
 "TUTUQUEN": "8490000",
 "RENGO": "2940000",
 "MALLOA": "2950000",
 "SAN VICENTE DE TAGUA TAGUA": "2970000",
 "SAN FERNANDO": "3070000",
 "ANGOSTURA": "3071000",
 "PUENTE NEGRO": "3072000",
 "CHIMBARONGO": "3090000",
 "NANCAGUA": "3110000",
 "CHEPICA": "3120000",
 "SANTA CRUZ": "3130000",
 "LOLOL": "3140000",
 "PUMANQUE": "3150000",
 "PALMILLA": "3160000",
 "PERALILLO SAN FERNANDO": "3170000",
 "PICHILEMU": "3220000",
 "NAVIDAD": "3230000",
 "LITUECHE": "3240000",
 "LA ESTRELLA": "3250000",
 "MARCHIHUE": "3260000",
 "PAREDONES": "3270000",
 "CUNACO": "3471000",
 "PANIAHUE": "3472000",
 "PELEQUEN": "3473000",
 "PLACILLA SAN FERNANDO": "3474000",
 "ROSARIO": "3480000",
 "TALCA": "3460000",
 "CUMPEO": "3481000",
 "PUTU": "3482000",
 "SAN RAFAEL": "3490000",
 "PELARCO": "3500000",
 "RIO CLARO": "3510000",
 "SAN CLEMENTE": "3520000",
 "MAULE": "3530000",
 "EMPEDRADO": "3540000",
 "PENCAHUE": "3550000",
 "CONSTITUCION": "3560000",
 "VILLA ALEGRE": "3650000",
 "SAN JAVIER": "3660000",
 "LINARES": "3580000",
 "CURANIPE": "3581000",
 "PANIMAVIDA": "3582000",
 "YERBAS BUENAS": "3600000",
 "COLBUN": "3610000",
 "LONGAVI": "3620000",
 "PARRAL": "3630000",
 "RETIRO": "3640000",
 "CAUQUENES": "3690000",
 "PELLUHUE": "3710000",
 "CHANCO": "3720000",
 "CHILLAN": "3780000",
 "SANTA CLARA": "3812000",
 "CHILLAN VIEJO": "3820000",
 "SAN CARLOS": "3840000",
 "NIQUEN": "3850000",
 "SAN FABIAN": "3860000",
 "COIHUECO": "3870000",
 "PINTO": "3880000",
 "SAN IGNACIO": "3890000",
 "EL CARMEN": "3900000",
 "PEMUCO": "3910000",
 "BULNES": "3930000",
 "QUILLON": "3940000",
 "RANQUIL": "3950000",
 "PORTEZUELO": "3960000",
 "COELEMU": "3970000",
 "COBQUECURA": "3990000",
 "QUIRIHUE": "4000000",
 "NINHUE": "4010000",
 "SAN NICOLAS": "4020000",
 "CONCEPCION": "4030000",
 "COLCURA": "4051000",
 "HUALPENCILLO": "4060000",
 "LARAQUETE": "4061000",
 "LENGA": "4070000",
 "LIRQUEN": "4080000",
 "LOTA ALTO": "4081000",
 "LOTA BAJO": "4090000",
 "TUBUL": "4091000",
 "CHIGUAYANTE": "4100000",
 "SAN PEDRO DE LA PAZ": "4120000",
 "PENCO": "4140000",
 "TOME": "4160000",
 "FLORIDA": "4170000",
 "HUALQUI": "4180000",
 "CORONEL": "4190000",
 "LOTA": "4210000",
 "SANTA JUANA": "4230000",
 "TALCAHUANO": "4260000",
 "LEBU": "4350000",
 "ARAUCO": "4360000",
 "CARAMPANGUE": "4361000",
 "CURANILAHUE": "4370000",
 "LOS ALAMOS": "4380000",
 "CANETE": "4390000",
 "HUALPEN": "4600000",
 "YUNGAY": "3920000",
 "CANTERA": "4202000",
 "HUEPIL": "4430000",
 "COIHUE": "4431000",
 "LOS ANGELES": "4440000",
 "MONTEAGUILA": "4441000",
 "PANGUE": "4442000",
 "SALTO DEL LAJA": "4450000",
 "SANTA FE": "4451000",
 "CABRERO": "4470000",
 "TUCAPEL": "4480000",
 "ANTUCO": "4490000",
 "QUILLECO": "4500000",
 "SANTA BARBARA": "4510000",
 "QUILACO": "4520000",
 "MULCHEN": "4530000",
 "NEGRETE": "4540000",
 "NACIMIENTO": "4550000",
 "LAJA": "4560000",
 "SAN ROSENDO": "4570000",
 "YUMBEL": "4580000",
 "RALCO": "4590000",
 "TIRUA": "4410000",
 "LONQUIMAY": "4690000",
 "CURACAUTIN": "4700000",
 "TEMUCO": "4780000",
 "CAJON TEMUCO": "4813000",
 "LABRANZA": "4814000",
 "PADRE LAS CASAS": "4850000",
 "QUEPE": "4851000",
 "LAUTARO": "4860000",
 "PILLALELBUN": "4861000",
 "PERQUENCO": "4870000",
 "VILCUN": "4880000",
 "CUNCO": "4890000",
 "MELIPEUCO": "4900000",
 "FREIRE": "4940000",
 "PITRUFQUEN": "4950000",
 "GORBEA": "4960000",
 "TOLTEN": "4980000",
 "TEODORO SCHMIDT": "4990000",
 "PUERTO SAAVEDRA": "5000000",
 "CARAHUE": "5010000",
 "NUEVA IMPERIAL": "5020000",
 "CHOLCHOL": "5040000",
 "MALALHUE": "4812000",
 "CURARREHUE": "4910000",
 "PUCON": "4920000",
 "LICAN RAY": "4921000",
 "VILLARRICA": "4930000",
 "LONCOCHE": "4970000",
 "LANCO": "5160000",
 "PANGUIPULLI": "5210000",
 "VALDIVIA": "5090000",
 "CIRUELOS": "5101000",
 "LOS MOLINOS": "5102000",
 "NIEBLA": "5110000",
 "PICHOY": "5111000",
 "REUMEN": "5112000",
 "SAN JOSE DE MARIQUINA": "5150000",
 "LOS LAGOS": "5170000",
 "FUTRONO": "5180000",
 "CORRAL": "5190000",
 "MAFIL": "5200000",
 "PAILLACO": "5230000",
 "CONTULMO": "4400000",
 "ANGOL": "4650000",
 "RENAICO": "4670000",
 "COLLIPULLI": "4680000",
 "ERCILLA": "4710000",
 "VICTORIA": "4720000",
 "TRAIGUEN": "4730000",
 "LUMACO": "4740000",
 "PUREN": "4750000",
 "LOS SAUCES": "4760000",
 "GALVARINO": "5030000",
 "MININCO": "5100000",
 "LA UNION": "5220000",
 "RIO BUENO": "5240000",
 "LAGO RANCO": "5250000",
 "OSORNO": "5290000",
 "PUYEHUE": "5360000",
 "PUERTO OCTAY": "5370000",
 "PURRANQUE": "5380000",
 "RIO NEGRO": "5390000",
 "SAN JUAN DE LA COSTA": "5400000",
 "ENTRE LAGOS": "5501000",
 "MISION SAN JUAN": "5502000",
 "MISION QUILACAHUIN": "5503000",
 "SAN PABLO LA UNION": "5504000",
 "PUERTO MONTT": "5480000",
 "ALERCE": "5505000",
 "HORNOPIREN": "5506000",
 "CHAMIZA": "5507000",
 "CHINQUIHUE": "5520000",
 "PARGUA": "5521000",
 "PIEDRA AZUL": "5522000",
 "PUERTO VARAS": "5550000",
 "NUEVA BRAUNAU": "5551000",
 "COCHAMO": "5560000",
 "CALBUCO": "5570000",
 "MAULLIN": "5580000",
 "LOS MUERMOS": "5590000",
 "FRESIA": "5600000",
 "LLANQUIHUE": "5610000",
 "FRUTILLAR": "5620000",
 "CHAITEN": "5850000",
 "HUALAIHUE": "5860000",
 "FUTALEUFU": "5870000",
 "ALTO PALENA": "5880000",
 "CASTRO": "5700000",
 "ANCUD": "5710000",
 "QUEMCHI": "5720000",
 "DALCAHUE": "5730000",
 "CURACO DE VELEZ": "5740000",
 "QUINCHAO": "5750000",
 "PUQUELDON": "5760000",
 "CHONCHI": "5770000",
 "QUEILEN": "5780000",
 "QUELLON": "5790000",
 "ACHAO": "5951000",
 "CHACAO": "5952000",
 "COYHAYQUE": "5950000",
 "PUERTO AYSEN": "6000000",
 "PUERTO CISNES": "6010000",
 "CHILE CHICO": "6050000",
 "COCHRANE": "6100000",
 "PUERTO NATALES": "6160000",
 "TORRES DEL PAINE": "6170000",
 "PUNTA ARENAS": "6200000",
 "RIO VERDE": "6240000",
 "CERRO SOMBRERO": "6250000",
 "SAN GREGORIO": "6260000",
 "PORVENIR": "6300000",
 "PRIMAVERA": "6310000"
}